scooter/__init__.py
scooter/build_script.py
scooter/gcc.py
scooter/llvm.py
scooter/remote_vs.py
scooter/scooter.py
scooter-2.8.dist-info/METADATA
scooter-2.8.dist-info/WHEEL
scooter-2.8.dist-info/top_level.txt
scooter-2.8.dist-info/RECORD
