Metadata-Version: 2.1
Name: scooter
Version: 2.8
Summary: UNKNOWN
Home-page: UNKNOWN
Author: UNKNOWN
Author-email: UNKNOWN
License: UNKNOWN
Platform: UNKNOWN
Requires-Dist: quickfiles
Requires-Dist: quickstructures
Requires-Dist: ellbur-easyrun
Requires-Dist: treewatcher
